spectroscopicbinarysystem/__init__.py
SpectroscopicBinarySystem-1.5.0.dist-info/LICENSE
SpectroscopicBinarySystem-1.5.0.dist-info/METADATA
SpectroscopicBinarySystem-1.5.0.dist-info/WHEEL
SpectroscopicBinarySystem-1.5.0.dist-info/top_level.txt
SpectroscopicBinarySystem-1.5.0.dist-info/RECORD
