Metadata-Version: 2.1
Name: SpectroscopicBinarySystem
Version: 1.5.0
Summary: Python astronomy tools for spectroscopic binary system
Author: Guillaume Bertrand
Author-email: gbe.io@pm.me
License: BSD-3-Clause
Keywords: astronomy,astrophysics,science,fits,models,fitting,spectroscopy,spectrum
Requires-Python: >=3.10
License-File: LICENSE
Requires-Dist: astropy (>=5.2.2)
Requires-Dist: astroquery (>=0.4.6)
Requires-Dist: BinaryStarSolver (>=1.2.0)
Requires-Dist: matplotlib (>=3.7.1)
Requires-Dist: numpy (>=1.24.2)
Requires-Dist: OrbitalPy (>=0.7.0)
Requires-Dist: PyYAML (>=6.0)
Requires-Dist: specutils (>=1.9.1)
Requires-Dist: plotly (>=5.14.1)
